orsvm/__init__.py
orsvm/kernels.py
orsvm/orsvm.py
orsvm-1.0.5.dist-info/LICENSE.txt
orsvm-1.0.5.dist-info/METADATA
orsvm-1.0.5.dist-info/WHEEL
orsvm-1.0.5.dist-info/top_level.txt
orsvm-1.0.5.dist-info/RECORD
