Metadata-Version: 2.1
Name: orsvm
Version: 1.0.5
Summary: SVM with Orthogonal Kernel functions of fractional order and normal
Home-page: https://github.com/AmirHoseinHadian/orsvm
Download-URL: https://github.com/AmirHoseinHadian/orsvm/archive/refs/tags/v1.0.5.tar.gz
Author: Amir Hossein Hadian Rasenan, Sherwin Nedaei Janbesaraei, Amirreza Azmoon, Mohammad Akhavan, Shakiba Amirshahi
Author-email: amir.h.hadian@gmail.com
Keywords: SVM,Orthogonal Polynomials,Classification,Chebyshev,Legendre,Gegenbauer,Jacobi
Classifier: Development Status :: 5 - Production/Stable
Classifier: Programming Language :: Python :: 3
Classifier: License :: OSI Approved :: MIT License
Classifier: Operating System :: OS Independent
Classifier: Topic :: Scientific/Engineering :: Artificial Intelligence
Requires-Python: >=3.8
License-File: LICENSE.txt
Requires-Dist: Cython
Requires-Dist: cvxopt
Requires-Dist: numpy
Requires-Dist: pandas
Requires-Dist: scikit-learn
Requires-Dist: sphinx
Requires-Dist: ipykernel
Requires-Dist: nbsphinx
